math_eval/Equation.py
math_eval/__init__.py
math_eval/math_eval.py
math_eval/test_math_eval.py
math_eval-0.2.4.dist-info/LICENSE
math_eval-0.2.4.dist-info/METADATA
math_eval-0.2.4.dist-info/WHEEL
math_eval-0.2.4.dist-info/top_level.txt
math_eval-0.2.4.dist-info/RECORD
