Metadata-Version: 2.1
Name: math-eval
Version: 0.2.4
Summary: Tool for safe (or less safe) evaluation of strings as math expressions
Home-page: https://github.com/molsonkiko/math_eval
Author: Mark Johnston Olson
Author-email: mjolsonsfca@gmail.com
License: MIT/X
Keywords: math,safe eval tool
Platform: UNKNOWN
Classifier: Programming Language :: Python
Classifier: Programming Language :: Python :: 3.6
Classifier: Programming Language :: Python :: 3.7
Classifier: Programming Language :: Python :: 3.8
Classifier: Programming Language :: Python :: 3.9
Classifier: Programming Language :: Python :: 3 :: Only
Classifier: Development Status :: 5 - Production/Stable
Classifier: Environment :: Console
Classifier: Intended Audience :: Developers
Classifier: Intended Audience :: Science/Research
Classifier: License :: OSI Approved :: MIT License
Classifier: Topic :: Text Processing
Requires-Python: >=3.6
License-File: LICENSE
Provides-Extra: test_math_eval
Requires-Dist: pandas ; extra == 'test_math_eval'
